mateoperaciones/__init__.py
mateoperaciones/modulo.py
mateoperaciones-0.1.2.dist-info/METADATA
mateoperaciones-0.1.2.dist-info/WHEEL
mateoperaciones-0.1.2.dist-info/top_level.txt
mateoperaciones-0.1.2.dist-info/RECORD
