Metadata-Version: 2.1
Name: mateoperaciones
Version: 0.1.2
Summary: libreria de operaciones básicas
Author: Alexis Ruales
License: MIT
Requires-Python: >=3.10.12
